karo/__init__.py
karo/cli/__init__.py
karo/cli/main.py
karo/cli/serve_command.py
karo/cli/token_command.py
karo/core/README.md
karo/core/__init__.py
karo/core/base_agent.py
karo/memory/README.md
karo/memory/__init__.py
karo/memory/conversation_history.py
karo/memory/memory_manager.py
karo/memory/memory_models.py
karo/memory/services/__init__.py
karo/memory/services/chromadb_service.py
karo/memory/tools/__init__.py
karo/memory/tools/memory_query_tool.py
karo/memory/tools/memory_store_tool.py
karo/prompts/README.md
karo/prompts/__init__.py
karo/prompts/system_prompt_builder.py
karo/providers/README.md
karo/providers/__init__.py
karo/providers/anthropic_provider.py
karo/providers/base_provider.py
karo/providers/gemini_provider.py
karo/providers/ollama_provider.py
karo/providers/openai_provider.py
karo/schemas/__init__.py
karo/schemas/base_schemas.py
karo/serving/__init__.py
karo/serving/auth.py
karo/serving/config.py
karo/serving/models.py
karo/serving/server.py
karo/sessions/database_service.py
karo/sessions/event.py
karo/sessions/service.py
karo/sessions/session.py
karo/tools/README.md
karo/tools/__init__.py
karo/tools/base_tool.py
karo/tools/calculator_tool.py
karo/tools/csv_reader_tool.py
karo/tools/document_reader_tool.py
karo/tools/excel_reader_tool.py
karo/utils/__init__.py
karo/utils/base_ingestion_script.py
karo/utils/logging_config.py
karo-0.4.1.dist-info/LICENSE
karo-0.4.1.dist-info/METADATA
karo-0.4.1.dist-info/WHEEL
karo-0.4.1.dist-info/RECORD
