Metadata-Version: 2.3
Name: karo
Version: 0.4.1
Summary: Modular Python framework for building AI agents with persistent memory
License: Apache-2.0
Author: Mensterra
Author-email: support@mensterra.com
Requires-Python: >=3.10,<4.0
Classifier: License :: OSI Approved :: Apache Software License
Classifier: Programming Language :: Python :: 3
Classifier: Programming Language :: Python :: 3.10
Classifier: Programming Language :: Python :: 3.11
Classifier: Programming Language :: Python :: 3.12
Classifier: Programming Language :: Python :: 3.13
Provides-Extra: memory
Provides-Extra: oauth
Provides-Extra: serve
Requires-Dist: Authlib (>=1.3.1) ; extra == "oauth"
Requires-Dist: anthropic (>=0.20.0)
Requires-Dist: chromadb (>=1.0.5,<2.0.0) ; extra == "memory"
Requires-Dist: click (>=8.1.7) ; extra == "serve"
Requires-Dist: email-validator (>=2.2.0,<3.0.0)
Requires-Dist: fastapi (>=0.115.9) ; extra == "serve"
Requires-Dist: google-generativeai (>=0.5.0,<1.0.0)
Requires-Dist: groq (>=0.5.0,<1.0.0)
Requires-Dist: instructor (>=1.7.9,<2.0.0)
Requires-Dist: jsonref (>=0.2,<1.0)
Requires-Dist: openai (>=1.75.0,<2.0.0)
Requires-Dist: openpyxl (>=3.1.0)
Requires-Dist: pandas (>=2.0.0)
Requires-Dist: pydantic (>=2.11.3,<3.0.0)
Requires-Dist: pypdf (>=4.0.0)
Requires-Dist: python-docx (>=1.0.0)
Requires-Dist: python-jose[cryptography] (>=3.3.0) ; extra == "serve"
Requires-Dist: pyyaml (>=6.0.1) ; extra == "serve"
Requires-Dist: sqlalchemy (>2.0.0)
Requires-Dist: tabulate (>=0.9.0)
Requires-Dist: uvicorn[standard] (>=0.30.0) ; extra == "serve"
